{
  "parent": "minecraft:recipes/root",
  "rewards": {
    "recipes": [
      "minecraft:raw_rabbit"
    ]
  },
  "criteria": {
    "raw_rabbit": {
      "trigger": "minecraft:inventory_changed",
      "conditions": {
        "items": [
          {
            "items": [
              "minecraft:rabbit"
            ]
          }
        ]
      }
    },
    "has_the_recipe": {
      "trigger": "minecraft:recipe_unlocked",
      "conditions": {
        "recipe": "minecraft:raw_rabbit"
      }
    }
  },
  "requirements": [
    [
      "raw_rabbit",
      "has_the_recipe"
    ]
  ]
}